[
  {
    "type": "planting",
    "dateStr": "20250814",
    "json": {
      "plantingRef": "20250814-上原(うずら角)-藍天"
    },
    "csv": "2025-08-14,山本 雅彦／山本 咲子／山本 直輝,上原(うずら角),藍天,20250711-藍天-01,10688,128,34,60,2025-11,＋種苗評の試験品種11枚,machine1,naoki,20250814-上原(うずら角)-藍天\n",
    "loggedAt": "2026-03-03T12:27:23.451Z"
  },
  {
    "type": "planting",
    "dateStr": "20250814",
    "json": {
      "plantingRef": "20250814-しあわせ地蔵-藍天"
    },
    "csv": "2025-08-14,山本 雅彦／山本 咲子／山本 直輝,しあわせ地蔵,藍天,20250711-藍天-01,10688,128,34,60,2025-11,＋種苗評の試験品種11枚,machine1,naoki,20250814-しあわせ地蔵-藍天\n",
    "loggedAt": "2026-03-03T12:28:17.702Z"
  },
  {
    "type": "planting",
    "dateStr": "20250814",
    "json": {
      "plantingRef": "20250814-しあわせ地蔵-藍天"
    },
    "csv": "2025-08-14,山本 雅彦／山本 咲子／山本 直輝,しあわせ地蔵,藍天,20250711-藍天-01,10688,128,33,60,2025-11,＋種苗評の試験品種11枚,machine1,naoki,20250814-しあわせ地蔵-藍天\n",
    "loggedAt": "2026-03-03T12:29:31.015Z"
  },
  {
    "type": "planting",
    "dateStr": "20250814",
    "json": {
      "plantingRef": "20250814-しあわせ地蔵-はやとよ"
    },
    "csv": "2025-08-14,山本 雅彦／山本 咲子／山本 直輝,しあわせ地蔵,はやとよ,20250711-はやとよ-01,1984,128,33,60,2025-11,南側,machine1,naoki,20250814-しあわせ地蔵-はやとよ\n",
    "loggedAt": "2026-03-03T12:30:32.969Z"
  },
  {
    "type": "planting",
    "dateStr": "20250814",
    "json": {
      "plantingRef": "20250814-三角畑-藍天"
    },
    "csv": "2025-08-14,山本 雅彦／山本 咲子／山本 直輝,三角畑,藍天,20250711-藍天-01,256,128,33,60,2025-11,先端,machine1,naoki,20250814-三角畑-藍天\n",
    "loggedAt": "2026-03-03T12:31:57.449Z"
  }
]
